{
  "rows": [
    {
      "id": 1,
      "rank": 1,
      "title": "认识观世音菩萨 增福增慧的法门",
      "category": "新闻法汛",
      "redStatus":0,
      "creator": "孙健炜",
      "createDate": "2017-04-21 18:12:07",
      "lastChange": "2017-04-22 18:12:07",
      "status": 0
    },
    {
      "id": 2,
      "rank": 2,
      "title": "认识观世音菩萨 增福增慧的法门",
      "category": "新闻法汛",
      "redStatus":1,
      "creator": "孙健炜",
      "createDate": "2017-04-21 18:12:07",
      "lastChange": "2017-04-22 18:12:07",
      "status": 1
    },
    {
      "id": 3,
      "rank": 3,
      "title": "认识观世音菩萨 增福增慧的法门",
      "category": "新闻法汛",
      "redStatus":0,
      "creator": "孙健炜",
      "createDate": "2017-04-21 18:12:07",
      "lastChange": "2017-04-22 18:12:07",
      "status": 1
    },
    {
      "id": 4,
      "rank": 4,
      "title": "认识观世音菩萨 增福增慧的法门",
      "category": "新闻法汛",
      "redStatus":1,
      "creator": "孙健炜",
      "createDate": "2017-04-21 18:12:07",
      "lastChange": "2017-04-22 18:12:07",
      "status": 0
    },
    {
      "id": 5,
      "rank": 5,
      "title": "认识观世音菩萨 增福增慧的法门",
      "category": "新闻法汛",
      "redStatus":1,
      "creator": "孙健炜",
      "createDate": "2017-04-21 18:12:07",
      "lastChange": "2017-04-22 18:12:07",
      "status": 0
    },
    {
      "id": 6,
      "rank": 6,
      "title": "认识观世音菩萨 增福增慧的法门",
      "category": "新闻法汛",
      "redStatus":0,
      "creator": "孙健炜",
      "createDate": "2017-04-21 18:12:07",
      "lastChange": "2017-04-22 18:12:07",
      "status": 0
    },
    {
      "id": 7,
      "rank": 7,
      "title": "认识观世音菩萨 增福增慧的法门",
      "category": "新闻法汛",
      "redStatus":0,
      "creator": "孙健炜",
      "createDate": "2017-04-21 18:12:07",
      "lastChange": "2017-04-22 18:12:07",
      "status": 0
    },
    {
      "id": 8,
      "rank": 8,
      "title": "认识观世音菩萨 增福增慧的法门",
      "category": "新闻法汛",
      "redStatus":0,
      "creator": "孙健炜",
      "createDate": "2017-04-21 18:12:07",
      "lastChange": "2017-04-22 18:12:07",
      "status": 0
    },
    {
      "id": 9,
      "rank": 9,
      "title": "认识观世音菩萨 增福增慧的法门",
      "category": "新闻法汛",
      "redStatus":0,
      "creator": "孙健炜",
      "createDate": "2017-04-21 18:12:07",
      "lastChange": "2017-04-22 18:12:07",
      "status": 0
    },
    {
      "id": 10,
      "rank": 10,
      "title": "认识观世音菩萨 增福增慧的法门",
      "category": "新闻法汛",
      "redStatus":0,
      "creator": "孙健炜",
      "createDate": "2017-04-21 18:12:07",
      "lastChange": "2017-04-22 18:12:07",
      "status": 0
    },
    {
      "id": 11,
      "rank": 11,
      "title": "认识观世音菩萨 增福增慧的法门",
      "category": "新闻法汛",
      "redStatus":0,
      "creator": "孙健炜",
      "createDate": "2017-04-21 18:12:07",
      "lastChange": "2017-04-22 18:12:07",
      "status": 0
    },
    {
      "id": 12,
      "rank": 12,
      "title": "认识观世音菩萨 增福增慧的法门",
      "category": "新闻法汛",
      "redStatus":0,
      "creator": "孙健炜",
      "createDate": "2017-04-21 18:12:07",
      "lastChange": "2017-04-22 18:12:07",
      "status": 0
    },
    {
      "id": 13,
      "rank": 13,
      "title": "认识观世音菩萨 增福增慧的法门",
      "category": "新闻法汛",
      "redStatus":0,
      "creator": "孙健炜",
      "createDate": "2017-04-21 18:12:07",
      "lastChange": "2017-04-22 18:12:07",
      "status": 0
    },
    {
      "id": 14,
      "rank": 14,
      "title": "认识观世音菩萨 增福增慧的法门",
      "category": "新闻法汛",
      "redStatus":0,
      "creator": "孙健炜",
      "createDate": "2017-04-21 18:12:07",
      "lastChange": "2017-04-22 18:12:07",
      "status": 0
    },
    {
      "id": 15,
      "rank": 15,
      "title": "认识观世音菩萨 增福增慧的法门",
      "category": "新闻法汛",
      "redStatus":0,
      "creator": "孙健炜",
      "createDate": "2017-04-21 18:12:07",
      "lastChange": "2017-04-22 18:12:07",
      "status": 0
    }
  ]
}